spark_dsg/__init__.py
spark_dsg/__main__.py
spark_dsg/_dsg_bindings.cpython-312-x86_64-linux-gnu.so
spark_dsg/io.py
spark_dsg/mp3d.py
spark_dsg/networkx.py
spark_dsg/open3d_visualization.py
spark_dsg/torch_conversion.py
spark_dsg/visualization.py
spark_dsg/zmq.py
spark_dsg/commands/visualize.py
spark_dsg/commands/zmq.py
spark_dsg-1.1.1.dist-info/METADATA
spark_dsg-1.1.1.dist-info/WHEEL
spark_dsg-1.1.1.dist-info/entry_points.txt
spark_dsg-1.1.1.dist-info/RECORD
spark_dsg-1.1.1.dist-info/licenses/LICENSE
