Metadata-Version: 2.4
Name: spark_dsg
Version: 1.1.1
Summary: Library for representing 3D scene graphs
Author-Email: Nathan Hughes <na26933@mit.edu>, Yun Chang <yunchang@mit.edu>
Maintainer-Email: Nathan Hughes <na26933@mit.edu>
License-Expression: BSD-3-Clause
Classifier: Development Status :: 4 - Beta
Classifier: Programming Language :: Python :: 3
Project-URL: Repository, https://github.com/MIT-SPARK/Spark-DSG
Requires-Python: >=3.8
Requires-Dist: numpy
Requires-Dist: seaborn
Requires-Dist: shapely
Requires-Dist: zmq
Provides-Extra: viz
Requires-Dist: plotly; extra == "viz"
Requires-Dist: open3d>=0.17; extra == "viz"
Requires-Dist: scipy; extra == "viz"
